_pulsar.cpython-39-darwin.so
pulsar/__init__.py
pulsar/exceptions.py
pulsar/functions/__init__.py
pulsar/functions/context.py
pulsar/functions/function.py
pulsar/functions/serde.py
pulsar/schema/__init__.py
pulsar/schema/definition.py
pulsar/schema/schema.py
pulsar/schema/schema_avro.py
pulsar_client_sn-2.11.0.0.dist-info/METADATA
pulsar_client_sn-2.11.0.0.dist-info/WHEEL
pulsar_client_sn-2.11.0.0.dist-info/top_level.txt
pulsar_client_sn-2.11.0.0.dist-info/RECORD
