Metadata-Version: 2.1
Name: pulsar-client-sn
Version: 2.11.0.0
Summary: Apache Pulsar Python client library
Home-page: https://pulsar.apache.org/
Author: Pulsar Devs
Author-email: dev@pulsar.apache.org
License: Apache License v2.0
Requires-Dist: certifi
Provides-Extra: all
Requires-Dist: apache-bookkeeper-client (>=4.9.2) ; extra == 'all'
Requires-Dist: fastavro (==0.24.0) ; extra == 'all'
Requires-Dist: grpcio (<1.28,>=1.8.2) ; extra == 'all'
Requires-Dist: prometheus-client ; extra == 'all'
Requires-Dist: protobuf (<=3.20.*,>=3.6.1) ; extra == 'all'
Requires-Dist: ratelimit ; extra == 'all'
Provides-Extra: avro
Requires-Dist: fastavro (==0.24.0) ; extra == 'avro'
Provides-Extra: functions
Requires-Dist: apache-bookkeeper-client (>=4.9.2) ; extra == 'functions'
Requires-Dist: grpcio (<1.28,>=1.8.2) ; extra == 'functions'
Requires-Dist: prometheus-client ; extra == 'functions'
Requires-Dist: protobuf (<=3.20.*,>=3.6.1) ; extra == 'functions'
Requires-Dist: ratelimit ; extra == 'functions'
